gurl/__init__.py
gurl-1.2.dist-info/LICENSE
gurl-1.2.dist-info/METADATA
gurl-1.2.dist-info/WHEEL
gurl-1.2.dist-info/entry_points.txt
gurl-1.2.dist-info/top_level.txt
gurl-1.2.dist-info/RECORD
