Metadata-Version: 2.1
Name: gurl
Version: 1.2
Summary: UCL MSc notes
Home-page: https://github.com/UCL-EO/gurl
Author: Prof. P. Lewis
Author-email: p.lewis@ucl.ac.uk
License: MIT
Keywords: scientific computing
Platform: UNKNOWN
Classifier: Development Status :: 3 - Alpha
Classifier: Intended Audience :: Developers
Classifier: Topic :: Software Development :: Build Tools
Classifier: License :: OSI Approved :: MIT License
Classifier: Programming Language :: Python :: 3.7
